app.py
anomaly_detector/__init__.py
anomaly_detector/config.py
anomaly_detector/facade.py
anomaly_detector/adapters/__init__.py
anomaly_detector/adapters/base_model_adapter.py
anomaly_detector/adapters/base_storage_adapter.py
anomaly_detector/adapters/feedback_strategy.py
anomaly_detector/adapters/som_model_adapter.py
anomaly_detector/adapters/som_storage_adapter.py
anomaly_detector/core/__init__.py
anomaly_detector/core/detector_pipeline.py
anomaly_detector/core/encoder.py
anomaly_detector/core/job.py
anomaly_detector/decorator/__init__.py
anomaly_detector/decorator/utils.py
anomaly_detector/exception/__init__.py
anomaly_detector/exception/exceptions.py
anomaly_detector/fact_store/__init__.py
anomaly_detector/fact_store/api.py
anomaly_detector/fact_store/app.py
anomaly_detector/fact_store/model.py
anomaly_detector/fact_store/templates/index.html
anomaly_detector/model/__init__.py
anomaly_detector/model/base_model.py
anomaly_detector/model/som_model.py
anomaly_detector/model/sompy_model.py
anomaly_detector/model/w2v_model.py
anomaly_detector/storage/__init__.py
anomaly_detector/storage/es_storage.py
anomaly_detector/storage/kafka_storage.py
anomaly_detector/storage/local_directory_storage.py
anomaly_detector/storage/local_storage.py
anomaly_detector/storage/stdout_sink.py
anomaly_detector/storage/storage.py
anomaly_detector/storage/storage_attribute.py
anomaly_detector/storage/storage_catalog.py
anomaly_detector/storage/storage_proxy.py
anomaly_detector/storage/storage_sink.py
anomaly_detector/storage/storage_source.py
tests/__init__.py
tests/conftest.py
tests/test_factstore.py
tests/test_false_anomaly_check.py
tests/test_pipeline_jobs.py
tests/test_som.py
tests/test_storage_catalog.py
tests/test_storage_proxy.py
tests/test_valid_storage.py
tests/test_validation_data.py
tests/test_w2v.py
tests/e2e/__init__.py
tests/e2e/conftest.py
tests/e2e/test_openshift_deployments.py
tests/e2e/util.py
log_anomaly_detector-0.0.2.dist-info/LICENSE.rst
log_anomaly_detector-0.0.2.dist-info/METADATA
log_anomaly_detector-0.0.2.dist-info/WHEEL
log_anomaly_detector-0.0.2.dist-info/entry_points.txt
log_anomaly_detector-0.0.2.dist-info/top_level.txt
log_anomaly_detector-0.0.2.dist-info/RECORD
