Metadata-Version: 2.1
Name: log-anomaly-detector
Version: 0.0.2
Summary: Log anomaly detector for streaming logs
Home-page: https://github.com/AICoE/log-anomaly-detector
Author: Zak Hassan
Author-email: zak.hassan@redhat.com
License: UNKNOWN
Platform: UNKNOWN
Classifier: Development Status :: 1 - Planning
Classifier: Natural Language :: English
Classifier: Programming Language :: Python :: 3.6
Requires-Python: >3.5
Requires-Dist: Click
Requires-Dist: python-dateutil (==2.6.1)
Requires-Dist: elasticsearch5
Requires-Dist: gensim
Requires-Dist: matplotlib
Requires-Dist: numpy
Requires-Dist: pandas
Requires-Dist: prometheus-client
Requires-Dist: Flask (==1.0.4)
Requires-Dist: scikit-learn
Requires-Dist: scipy
Requires-Dist: tqdm
Requires-Dist: SQLAlchemy
Requires-Dist: PyMySQL
Requires-Dist: LAD-SOMPY
Requires-Dist: pyyaml
Requires-Dist: numba
Requires-Dist: kafka-python
Requires-Dist: jaeger-client
Requires-Dist: tornado (==5.1.1)
Requires-Dist: opentracing-instrumentation
Requires-Dist: prometheus-flask-exporter
